loopa/__init__.py
loopa/core.py
loopa/exceptions.py
loopa/utils.py
loopa-0.0.2.dist-info/DESCRIPTION.rst
loopa-0.0.2.dist-info/METADATA
loopa-0.0.2.dist-info/RECORD
loopa-0.0.2.dist-info/WHEEL
loopa-0.0.2.dist-info/metadata.json
loopa-0.0.2.dist-info/top_level.txt
